olivattam/__init__.py
olivattam/converter.py
olivattam/extractor.py
olivattam/utils.py
olivattam-0.0.3.dist-info/licenses/LICENSE
olivattam-0.0.3.dist-info/METADATA
olivattam-0.0.3.dist-info/WHEEL
olivattam-0.0.3.dist-info/top_level.txt
olivattam-0.0.3.dist-info/RECORD
