Metadata-Version: 2.4
Name: Olivattam
Version: 0.0.3
Summary: A package for extraction of major colors from the Images
Author: Dheena Krishna
Author-email: Dheena Krishna <dheenakrishna2020@gmail.com>
Maintainer: Dheena krishna
Maintainer-email: dheenakrishna2020@gmail.com
License-Expression: MIT
Project-URL: Homepage, https://github.com/Dheenack/olivattam
Project-URL: Issues, https://github.com/Dhenack/olivattam/issues
Classifier: Programming Language :: Python :: 3
Classifier: Operating System :: OS Independent
Requires-Python: >=3.6
License-File: LICENSE
Requires-Dist: pillow>=7.0.0
Dynamic: author
Dynamic: license-file
Dynamic: maintainer
Dynamic: maintainer-email
Dynamic: requires-python
